musktest/__init__.py
musktest/manage.py
musktest/core/DBClient.py
musktest/core/__init__.py
musktest/core/basecase.py
musktest/core/dataParser.py
musktest/core/generateCase.py
musktest/core/httptest.py
musktest/core/initEvn.py
musktest/core/logger.py
musktest/core/resultPush.py
musktest/core/testResult.py
musktest/core/testRunner.py
musktest/core/tools.py
musktest/templates/__init__.py
musktest/templates/http_demo/__init__.py
musktest/templates/http_demo/funcTools.py
musktest/templates/http_demo/run.py
musktest/templates/http_demo/settings.py
musktest/templates/http_demo/case_json/__init__.py
musktest/templates/http_demo/case_py/__init__.py
musktest/templates/http_demo/case_py/test_case_demo.py
musktest/templates/http_demo/case_yaml/__init__.py
musktest/templates/http_demo/logs/__init__.py
musktest/templates/http_demo/reports/__init__.py
musktest/templates/reports/__init__.py
musktest/templates/reports/dingtalk.md
musktest/templates/reports/templates03.html
musktest/templates/reports/templates1.html
musktest/templates/reports/templates2.html
musktest/templates/reports/templates3.html
musktest-2.2.1.dist-info/LICENSE
musktest-2.2.1.dist-info/METADATA
musktest-2.2.1.dist-info/WHEEL
musktest-2.2.1.dist-info/entry_points.txt
musktest-2.2.1.dist-info/top_level.txt
musktest-2.2.1.dist-info/RECORD
