Metadata-Version: 2.1
Name: musktest
Version: 2.2.1
Summary: a no code api testing framework
Home-page: https://github.com/musen123/MuskTest
Author: MuSen
Author-email: 121292679@qq.com
Classifier: Programming Language :: Python :: 3
Requires-Python: >=3.6
License-File: LICENSE
Requires-Dist: Jinja2 (==3.0.3)
Requires-Dist: PyYAML (==5.3.1)
Requires-Dist: requests (==2.24.0)
Requires-Dist: requests-toolbelt (==0.9.1)
Requires-Dist: PyMySQL (==1.0.2)
Requires-Dist: rsa (==4.7.2)
Requires-Dist: jsonpath (==0.82)
Requires-Dist: pyasn1 (==0.4.8)
Requires-Dist: faker (==8.11.0)
